aiotinder/__init__.py
aiotinder-0.1.0.dist-info/WHEEL
aiotinder-0.1.0.dist-info/METADATA
aiotinder-0.1.0.dist-info/RECORD
